sitecustomize.py
mustmatch/__init__.py
mustmatch/__main__.py
mustmatch/cli.py
mustmatch/pytest_plugin.py
mustmatch/version.py
mustmatch/services/__init__.py
mustmatch/services/comparator.py
mustmatch/services/fixture.py
mustmatch/services/normalizer.py
mustmatch/services/parser.py
mustmatch/services/runner.py
mustmatch-0.0.2.dist-info/METADATA
mustmatch-0.0.2.dist-info/WHEEL
mustmatch-0.0.2.dist-info/entry_points.txt
mustmatch-0.0.2.dist-info/top_level.txt
mustmatch-0.0.2.dist-info/RECORD
