Metadata-Version: 2.4
Name: mustmatch
Version: 0.0.2
Summary: CLI output assertion tool for documentation testing
Author-email: Ian Maurer <ian@genomoncology.com>
License: MIT
Project-URL: Homepage, https://github.com/genomoncology/mustmatch
Project-URL: Repository, https://github.com/genomoncology/mustmatch
Keywords: testing,documentation,cli,assertions
Classifier: Development Status :: 4 - Beta
Classifier: Environment :: Console
Classifier: Intended Audience :: Developers
Classifier: License :: OSI Approved :: MIT License
Classifier: Programming Language :: Python :: 3
Classifier: Programming Language :: Python :: 3.10
Classifier: Programming Language :: Python :: 3.11
Classifier: Programming Language :: Python :: 3.12
Classifier: Programming Language :: Python :: 3.13
Classifier: Topic :: Software Development :: Testing
Classifier: Topic :: Documentation
Requires-Python: >=3.10
Requires-Dist: mistune>=3.0
Provides-Extra: dev
Requires-Dist: pytest>=7.0; extra == "dev"
Requires-Dist: pytest-cov>=4.0; extra == "dev"
Requires-Dist: ruff>=0.1.0; extra == "dev"
